supers2/__init__.py
supers2/models/__init__.py
supers2/models/opensr_baseline/__init__.py
supers2/models/opensr_baseline/cnn.py
supers2/models/opensr_baseline/mamba.py
supers2/models/opensr_baseline/swin.py
supers2/models/tricks.py
supers2/nonreference.py
supers2/referencex2.py
supers2/referencex4.py
supers2/utils.py
supers2/xai/__init__.py
supers2/xai/lam.py
supers2/xai/utils.py
supers2-0.0.18.dist-info/LICENSE
supers2-0.0.18.dist-info/METADATA
supers2-0.0.18.dist-info/WHEEL
supers2-0.0.18.dist-info/RECORD
