Metadata-Version: 2.1
Name: supers2
Version: 0.0.18
Summary: SR for Sentinel-2
Home-page: https://github.com/IPL-UV/supers2
Author: Julio Contreras
Author-email: julio.contreras@uv.es
Requires-Python: >=3.9,<4.0
Classifier: Programming Language :: Python :: 3
Classifier: Programming Language :: Python :: 3.9
Classifier: Programming Language :: Python :: 3.10
Classifier: Programming Language :: Python :: 3.11
Classifier: Programming Language :: Python :: 3.12
Requires-Dist: einops (>=0.8.0)
Requires-Dist: numpy (>=1.22.0)
Requires-Dist: timm (>=1.0.11)
Requires-Dist: torch (>2.1.0)
Project-URL: Documentation, https://ipl-uv.github.io/superS2/
Project-URL: Repository, https://github.com/IPL-UV/supers2
